DocTableFlow/__init__.py
DocTableFlow/_docTableExtractor.py
DocTableFlow/main.py
DocTableFlow-0.1.5.dist-info/LICENSE
DocTableFlow-0.1.5.dist-info/METADATA
DocTableFlow-0.1.5.dist-info/WHEEL
DocTableFlow-0.1.5.dist-info/top_level.txt
DocTableFlow-0.1.5.dist-info/RECORD
